{"components_ocapplicationicon.md":"hevXhoGZ","components_ocavatar.md":"4Afmq1oj","components_ocavatarcount.md":"DdJ8_OOe","components_ocavataritem.md":"DERCb_o4","components_ocavatars.md":"ByDch5l_","components_ocbreadcrumb.md":"quCUoyET","components_ocbutton.md":"D-ftnl-f","components_occheckbox.md":"Be0yIgun","components_occolorinput.md":"huJ3LPIQ","components_occontextualhelper.md":"DOJt7n9q","components_ocdatepicker.md":"BLD4nwYD","components_ocdefinitionlist.md":"BDqSdqTh","components_ocdrop.md":"C_La-PlY","components_ocdropzone.md":"Theu2UKK","components_ocemojipicker.md":"l4h5ASt3","components_ocerrorlog.md":"tkbXpwlM","components_ocfileinput.md":"u3I47fUB","components_ocfilterchip.md":"YdZMU9y2","components_ocgrid.md":"WcuViemf","components_ochiddenannouncer.md":"YLO_D0XS","components_ocicon.md":"fqIg5_Eu","components_ocimage.md":"uS0Dcm5i","components_ocinfodrop.md":"BCiaBnbV","components_oclist.md":"BS2t2sLu","components_ocloader.md":"C24_l6no","components_ocmodal.md":"DtXkCHB9","components_ocnotificationmessage.md":"C5vFbrbc","components_ocnotifications.md":"UBcuiqh8","components_ocpagesize.md":"tbUX9KCh","components_ocpagination.md":"CZWk4yN6","components_ocprogress.md":"ChYSEZcS","components_ocprogresspie.md":"BDDt9Iuz","components_ocradio.md":"DqQEkwMS","components_ocrecipient.md":"DmKKeydt","components_ocsearchbar.md":"I0eX84NY","components_ocselect.md":"Bx4nYnPH","components_ocspinner.md":"CQZEPPma","components_ocstatusindicators.md":"ftwi2GZA","components_ocswitch.md":"74TXwFE7","components_octable.md":"sI-nK4c6","components_octablesimple.md":"BDwgCiZl","components_octag.md":"BREbr1FD","components_octextarea.md":"CfJeD287","components_octextinput.md":"Cy4UkAVY","designtokens_colorpalette.md":"DjN08IF8","designtokens_colorroles.md":"Dv1mk6OI","designtokens_fontsizes.md":"DhWwicD3","designtokens_spacings.md":"B9afSRya","index.md":"DH89uoRm"}
