{"components_ocapplicationicon.md":"DASmUAA0","components_ocavatar.md":"DlqFl2So","components_ocavatarcount.md":"COkv6w53","components_ocavataritem.md":"BuPckBU8","components_ocavatars.md":"DbLmxFfl","components_ocbottomdrawer.md":"BIHjOTHh","components_ocbreadcrumb.md":"CfbxgTx_","components_ocbutton.md":"CTKXctv6","components_occard.md":"Bb0295a4","components_occheckbox.md":"D5pevcg1","components_occolorinput.md":"ZGq7-Vqn","components_occontextualhelper.md":"CBIiyt4Q","components_ocdatepicker.md":"CKq1ztf3","components_ocdefinitionlist.md":"Z3LCzGwB","components_ocdrop.md":"DpxjWx8j","components_ocdropzone.md":"DNAGoXKK","components_ocemojipicker.md":"B4sZrEZE","components_ocerrorlog.md":"Da5YNx5k","components_ocfileinput.md":"BJDZ5a3y","components_ocfilterchip.md":"DpS2sUfk","components_ocfloatingactionbutton.md":"Bzarceh-","components_ochiddenannouncer.md":"D9LpALa9","components_ocicon.md":"DsVxxPNR","components_ocimage.md":"B40wbGl-","components_ocinfodrop.md":"BtNEbbwF","components_oclist.md":"z7vrujZ3","components_ocloader.md":"D4lxmArL","components_ocmodal.md":"Ca41-YtV","components_ocnotificationmessage.md":"B4oPEMfm","components_ocnotifications.md":"GnPOdfmW","components_ocpagesize.md":"zX6cTR04","components_ocpagination.md":"C0n97hSy","components_ocprogress.md":"CJqwwGy2","components_ocprogresspie.md":"Bc0J2P4J","components_ocradio.md":"C7sTdisW","components_ocrecipient.md":"hNQrBtn3","components_ocsearchbar.md":"EZ1dCavS","components_ocselect.md":"CpV4mgV0","components_ocspinner.md":"CyQuC4oW","components_ocstatusindicators.md":"BC_B3EZb","components_ocswitch.md":"BbuxUJsK","components_octable.md":"BSz2lVMb","components_octablesimple.md":"Dkizj6YQ","components_octag.md":"gq5qJerd","components_octextarea.md":"CovspuYi","components_octextinput.md":"E0UJqd8b","designtokens_colorpalette.md":"CJRAjXdf","designtokens_colorroles.md":"D45gH-X6","gettingstarted_installation.md":"BsRT5CQt","gettingstarted_tailwindmigration.md":"C1359OOh","gettingstarted_usage.md":"ghKs77Dr","index.md":"D9R4r8kT"}
