{"components_ocapplicationicon.md":"DmbDeLq4","components_ocavatar.md":"DcsvEGLB","components_ocavatarcount.md":"I9H3WWBQ","components_ocavataritem.md":"DPeEmvtu","components_ocavatars.md":"DjZ-9BDE","components_ocbottomdrawer.md":"DMjxj_0x","components_ocbreadcrumb.md":"B79F95Qp","components_ocbutton.md":"J7ymSIGM","components_occheckbox.md":"Cx82sZyK","components_occolorinput.md":"BK1F6e4S","components_occontextualhelper.md":"B2Hca_oM","components_ocdatepicker.md":"BN2eC-Oc","components_ocdefinitionlist.md":"WcLWUC6Q","components_ocdrop.md":"Cx3UMD46","components_ocdropzone.md":"BvsSyAwx","components_ocemojipicker.md":"BIJGu2Mz","components_ocerrorlog.md":"DXGuhRqB","components_ocfileinput.md":"dBp_CqAH","components_ocfilterchip.md":"CKqhi-1D","components_ocgrid.md":"GEI00Jhp","components_ochiddenannouncer.md":"DSG26Mac","components_ocicon.md":"BDNMhm3C","components_ocimage.md":"C5VcPacU","components_ocinfodrop.md":"15NRBRfL","components_oclist.md":"ByREYUMd","components_ocloader.md":"DcCtCSwG","components_ocmodal.md":"CkTApvul","components_ocnotificationmessage.md":"CxjHMvl0","components_ocnotifications.md":"F1aXy0nj","components_ocpagesize.md":"DmrrqEtC","components_ocpagination.md":"ChR9AuVg","components_ocprogress.md":"BjGgvzFT","components_ocprogresspie.md":"Cglik2bR","components_ocradio.md":"Cv6lKuky","components_ocrecipient.md":"z-fBnAus","components_ocsearchbar.md":"BZacCa99","components_ocselect.md":"CUJ9uSVL","components_ocspinner.md":"X2uJH0fT","components_ocstatusindicators.md":"Du6tukD4","components_ocswitch.md":"DUQinrOF","components_octable.md":"BLw-jb5s","components_octablesimple.md":"DtDhRIOo","components_octag.md":"v-ADCpT9","components_octextarea.md":"CooiuS9G","components_octextinput.md":"lyKciAHo","designtokens_colorpalette.md":"DtZNiaXe","designtokens_colorroles.md":"DgqvaTJj","designtokens_fontsizes.md":"37SqXSl0","designtokens_spacings.md":"BOU4w-7M","index.md":"BhGMRv9D"}
