{"components_ocapplicationicon.md":"5qn9DMIO","components_ocavatar.md":"CLVKTqW5","components_ocavatarcount.md":"CokKOozE","components_ocavataritem.md":"Bv11gJLj","components_ocavatars.md":"nGYVJMoo","components_ocbottomdrawer.md":"BqJ-4X1t","components_ocbreadcrumb.md":"DtMxEKJK","components_ocbutton.md":"lB7Zvc1U","components_occard.md":"B_5cFGkC","components_occheckbox.md":"7IL1Lzar","components_occolorinput.md":"BO4N4O7e","components_occontextualhelper.md":"ByuWogEg","components_ocdatepicker.md":"D-fMF4Cu","components_ocdefinitionlist.md":"BWauDphv","components_ocdrop.md":"Boqb_hE8","components_ocdropzone.md":"lWYr6h0q","components_ocemojipicker.md":"BVbmOPM7","components_ocerrorlog.md":"0QjN31Lo","components_ocfileinput.md":"Cnkt9y6x","components_ocfilterchip.md":"NDmsHYT3","components_ochiddenannouncer.md":"DUwxuSZg","components_ocicon.md":"H2m7L-Rt","components_ocimage.md":"CGWI9lbe","components_ocinfodrop.md":"C3M4CbPs","components_oclist.md":"Bs8bNdwy","components_ocloader.md":"C8Aad98V","components_ocmodal.md":"lk0ejMQD","components_ocnotificationmessage.md":"BCeuQbKe","components_ocnotifications.md":"BlIceuUl","components_ocpagesize.md":"bQFlefl6","components_ocpagination.md":"B2cSDBPl","components_ocprogress.md":"BbXtab1i","components_ocprogresspie.md":"C7Q1zzkP","components_ocradio.md":"Bwbd-CIM","components_ocrecipient.md":"Bk7Hntau","components_ocsearchbar.md":"BiP7WUqr","components_ocselect.md":"BKXcsgc8","components_ocspinner.md":"CBkXjE0J","components_ocstatusindicators.md":"DHzPKg7a","components_ocswitch.md":"BGO53sjJ","components_octable.md":"Dcwy_g_I","components_octablesimple.md":"CL-HqQ5M","components_octag.md":"CUgppCjT","components_octextarea.md":"BWT3HQez","components_octextinput.md":"D9QUm4wo","designtokens_colorpalette.md":"49rV-z4h","designtokens_colorroles.md":"BMEL_qjj","gettingstarted_installation.md":"D94-h-xF","gettingstarted_tailwindmigration.md":"OBKcVAUy","gettingstarted_usage.md":"CSPCl7zD","index.md":"CeKJQQmA"}
