{"components_ocapplicationicon.md":"DknnJ9nT","components_ocavatar.md":"DZWFwVxb","components_ocavatarcount.md":"CBQZ3bdr","components_ocavataritem.md":"BQSPPR67","components_ocavatars.md":"CNx9Fsvn","components_ocbottomdrawer.md":"Cm12iHAc","components_ocbreadcrumb.md":"D6508qQA","components_ocbutton.md":"A4CyafOD","components_occard.md":"DOGblwEz","components_occheckbox.md":"D09KAwOs","components_occolorinput.md":"lyFfFvae","components_occontextualhelper.md":"DlsGZrRt","components_ocdatepicker.md":"Dpott-m5","components_ocdefinitionlist.md":"NaT-YW8l","components_ocdrop.md":"gqTcHXj5","components_ocdropzone.md":"DC6_9qmH","components_ocemojipicker.md":"I3tYpXNa","components_ocerrorlog.md":"CqBEyHgk","components_ocfileinput.md":"BfWtIxYB","components_ocfilterchip.md":"C5NOm3TC","components_ochiddenannouncer.md":"D3zNS19U","components_ocicon.md":"BcXLxulb","components_ocimage.md":"hteE9l-c","components_ocinfodrop.md":"CCu2Cv2L","components_oclist.md":"BEMfr2VG","components_ocloader.md":"BzEa6Vjg","components_ocmodal.md":"DIhSvTUe","components_ocnotificationmessage.md":"7NpUYDOE","components_ocnotifications.md":"B86syrIv","components_ocpagesize.md":"rv3cKQw0","components_ocpagination.md":"BK822-xZ","components_ocprogress.md":"BPkff_eu","components_ocprogresspie.md":"DYoYbHBq","components_ocradio.md":"DgZ2VjYV","components_ocrecipient.md":"BFeF1nNv","components_ocsearchbar.md":"DpQovxVl","components_ocselect.md":"Bw6WY3uw","components_ocspinner.md":"3hVWlIYh","components_ocstatusindicators.md":"CzKLY7TV","components_ocswitch.md":"RXnyrz_L","components_octable.md":"tiwak6Sd","components_octablesimple.md":"hKGGydBW","components_octag.md":"DryiGBb0","components_octextarea.md":"DWoLJxPO","components_octextinput.md":"BsFAM53R","designtokens_colorpalette.md":"DniHhLTh","designtokens_colorroles.md":"COufSpwH","gettingstarted_installation.md":"Vtar5cvy","gettingstarted_tailwindmigration.md":"C-FNBDc5","gettingstarted_usage.md":"EA7NuJAo","index.md":"LqpD6uT3"}
