{"components_ocapplicationicon.md":"S6J3QVz8","components_ocavatar.md":"Cl-kZui1","components_ocavatarcount.md":"HNHbhwkI","components_ocavataritem.md":"BraF_yiH","components_ocavatars.md":"c00vIGrf","components_ocbottomdrawer.md":"Dl9dGMZT","components_ocbreadcrumb.md":"t48__O08","components_ocbutton.md":"DXHJxrp3","components_occard.md":"DgkpRv81","components_occheckbox.md":"Dem9nXPQ","components_occolorinput.md":"mjvy22E2","components_occontextualhelper.md":"BUzFQ0wP","components_ocdatepicker.md":"7ObBggDl","components_ocdefinitionlist.md":"CNwC0OxH","components_ocdrop.md":"CGsSQPYI","components_ocdropzone.md":"B7pZQXzx","components_ocemojipicker.md":"DGv5bg5H","components_ocerrorlog.md":"Cz3j6Kuf","components_ocfileinput.md":"D6EnATzX","components_ocfilterchip.md":"BPE0GGFe","components_ocfloatingactionbutton.md":"BTT9Q21x","components_ochiddenannouncer.md":"08PI8I4o","components_ocicon.md":"Dp0KXSo3","components_ocimage.md":"C_wVuR5U","components_ocinfodrop.md":"t7hUQKun","components_oclist.md":"Bdazpit7","components_ocloader.md":"zVm1FKud","components_ocmodal.md":"4x4Yu-EX","components_ocnotificationmessage.md":"BrGFyeiM","components_ocnotifications.md":"BsaPDRTy","components_ocpagesize.md":"DakYB9PF","components_ocpagination.md":"CHfNLI-4","components_ocprogress.md":"DbKuVKur","components_ocprogresspie.md":"CSF02ta8","components_ocradio.md":"BRajId8u","components_ocrecipient.md":"C4393Rj-","components_ocsearchbar.md":"B_e0Tfaw","components_ocselect.md":"B-MdyQ8h","components_ocspinner.md":"DDs9dAEy","components_ocstatusindicators.md":"DOxxo1gU","components_ocswitch.md":"KDamMRwy","components_octable.md":"-Wlqgxsi","components_octablesimple.md":"DujrqKu-","components_octag.md":"DJemUeG4","components_octextarea.md":"C2_lzZMG","components_octextinput.md":"DOc0u_LZ","designtokens_colorpalette.md":"D_oNsCDN","designtokens_colorroles.md":"Cr6ZMOqp","gettingstarted_installation.md":"DuWAjthO","gettingstarted_tailwindmigration.md":"CmR79fVB","gettingstarted_usage.md":"B5TIqAwc","index.md":"COBF95__"}
